SaskeYT/__init__.py
SaskeYT/downloader.py
SaskeYT-1.0.dist-info/LICENSE
SaskeYT-1.0.dist-info/METADATA
SaskeYT-1.0.dist-info/WHEEL
SaskeYT-1.0.dist-info/entry_points.txt
SaskeYT-1.0.dist-info/top_level.txt
SaskeYT-1.0.dist-info/RECORD
