Metadata-Version: 2.1
Name: SaskeYT
Version: 1.0
Summary: No tengo nada que decir
Home-page: https://github.com/sasukeyt77/PyPI-vamos-a-ver
Author: Sere22
Author-email: notengocorreo@gmail.com
Classifier: Programming Language :: Python :: 3
Classifier: License :: OSI Approved :: MIT License
Classifier: Operating System :: OS Independent
Requires-Python: >=3.6
License-File: LICENSE
Requires-Dist: requests
Requires-Dist: beautifulsoup4
